allure_ai_analyzer-1.0.7.dist-info/licenses/LICENSE
allure_analyzer/__init__.py
allure_analyzer/cli.py
allure_analyzer/server.py
allure_analyzer/analyzer/__init__.py
allure_analyzer/analyzer/core.py
allure_analyzer/analyzer/fingerprinter.py
allure_analyzer/analyzer/ingestion.py
allure_analyzer/analyzer/reporting.py
allure_analyzer/config/default_config.yaml
allure_analyzer/static/main.js
allure_analyzer/static/style.css
allure_analyzer/templates/report.html
allure_ai_analyzer-1.0.7.dist-info/METADATA
allure_ai_analyzer-1.0.7.dist-info/WHEEL
allure_ai_analyzer-1.0.7.dist-info/entry_points.txt
allure_ai_analyzer-1.0.7.dist-info/top_level.txt
allure_ai_analyzer-1.0.7.dist-info/RECORD
