Metadata-Version: 2.4
Name: allure-ai-analyzer
Version: 1.0.7
Summary: An intelligent CLI tool that transforms raw Allure test results into an interactive dashboard with an AI analyst.
Author-email: Keinar Elkayam <info@digital-solution.co.il>
Project-URL: Homepage, https://github.com/keinar/allure-ai-analyzer
Classifier: Programming Language :: Python :: 3
Classifier: License :: OSI Approved :: MIT License
Classifier: Operating System :: OS Independent
Requires-Python: >=3.11
License-File: LICENSE
Requires-Dist: PyYAML>=6.0
Requires-Dist: Flask>=3.0
Requires-Dist: python-dotenv>=1.0
Requires-Dist: google-genai>=0.3
Dynamic: license-file
